src/main.py
crypto_simulator-0.1.2.dist-info/METADATA
crypto_simulator-0.1.2.dist-info/WHEEL
crypto_simulator-0.1.2.dist-info/entry_points.txt
crypto_simulator-0.1.2.dist-info/top_level.txt
crypto_simulator-0.1.2.dist-info/RECORD
