Metadata-Version: 2.1
Name: crypto-simulator
Version: 0.1.2
Summary: A crypto trading simulator
Home-page: https://github.com/max-paul/crypto-simulator
Author: Max Paul
Author-email: maxkpaul21@gmail.com
Requires-Dist: ccxt ==4.1.50
Requires-Dist: matplotlib ==3.8.1
Requires-Dist: pandas ==2.1.3
Requires-Dist: tk ==0.1.0
